eai/compliance.py
eai/fairness.py
eai/monitoring.py
ethical_ai_validator/__init__.py
ethical_ai_validator/cli.py
ethical_ai_validator/ethical_ai_validator.py
ethical_ai_validator/core/__init__.py
ethical_ai_validator/core/validator.py
whis_ethical_ai-1.3.0.dist-info/licenses/LICENSE
whis_ethical_ai-1.3.0.dist-info/METADATA
whis_ethical_ai-1.3.0.dist-info/WHEEL
whis_ethical_ai-1.3.0.dist-info/entry_points.txt
whis_ethical_ai-1.3.0.dist-info/top_level.txt
whis_ethical_ai-1.3.0.dist-info/RECORD
