Metadata-Version: 2.4
Name: whis-ethical-ai
Version: 1.3.0
Summary: Comprehensive ethical AI validation and auditing package
Home-page: https://github.com/whis-19/ethical-ai
Author: Ethical AI Team
Author-email: Ethical AI Team <muhammadabdullahinbox@gmail.com>
Maintainer-email: Ethical AI Team <muhammadabdullahinbox@gmail.com>
License: MIT
Project-URL: Homepage, https://github.com/whis-19/ethical-ai
Project-URL: Documentation, https://whis-19.github.io/ethical-ai/
Project-URL: Repository, https://github.com/whis-19/ethical-ai
Project-URL: Bug Tracker, https://github.com/whis-19/ethical-ai/issues
Keywords: ethical-ai,bias-detection,fairness,ai-auditing,gdpr-compliance
Platform: any
Classifier: Development Status :: 4 - Beta
Classifier: Intended Audience :: Developers
Classifier: Intended Audience :: Science/Research
Classifier: License :: OSI Approved :: MIT License
Classifier: Operating System :: OS Independent
Classifier: Programming Language :: Python :: 2.7
Classifier: Topic :: Scientific/Engineering :: Artificial Intelligence
Classifier: Topic :: Software Development :: Libraries :: Python Modules
Classifier: Topic :: Software Development :: Testing
Requires-Python: >=2.7
License-File: LICENSE
Requires-Dist: numpy>=1.16.0
Requires-Dist: pandas>=0.20.0
Requires-Dist: scikit-learn>=0.20.0
Requires-Dist: reportlab>=3.4.0
Provides-Extra: dev
Requires-Dist: pytest>=4.0.0; extra == "dev"
Requires-Dist: pytest-cov>=2.0.0; extra == "dev"
Requires-Dist: pytest-mock>=2.0.0; extra == "dev"
Requires-Dist: black>=19.0.0; extra == "dev"
Requires-Dist: flake8>=3.0.0; extra == "dev"
Requires-Dist: mypy>=0.700; extra == "dev"
Requires-Dist: pre-commit>=1.0.0; extra == "dev"
Provides-Extra: docs
Requires-Dist: sphinx>=2.0.0; extra == "docs"
Requires-Dist: sphinx-rtd-theme>=0.4.0; extra == "docs"
Provides-Extra: full
Requires-Dist: matplotlib>=2.0.0; extra == "full"
Requires-Dist: seaborn>=0.9.0; extra == "full"
Requires-Dist: jupyter>=1.0.0; extra == "full"
Requires-Dist: notebook>=5.0.0; extra == "full"
Dynamic: author
Dynamic: home-page
Dynamic: license-file
Dynamic: platform
Dynamic: requires-python
